j1nuclei/__init__.py
j1nuclei/__main__.py
j1nuclei/cli.py
j1nuclei/config.py
j1nuclei/j1api.py
j1nuclei/j1auth.py
j1nuclei/nucleirunner.py
j1nuclei/runner.py
j1nuclei/targets_discovery.json
j1nuclei-1.0.3.dist-info/LICENSE
j1nuclei-1.0.3.dist-info/METADATA
j1nuclei-1.0.3.dist-info/WHEEL
j1nuclei-1.0.3.dist-info/entry_points.txt
j1nuclei-1.0.3.dist-info/top_level.txt
j1nuclei-1.0.3.dist-info/RECORD
